myhdl/vhdl/generated_myhdl/dffa.vhd
-- File: dffa.vhd
-- Generated by MyHDL 0.7
-- Date: Wed Apr 18 05:51:51 2012


library IEEE;
use IEEE.std_logic_1164.all;
use IEEE.numeric_std.all;
use std.textio.all;

use work.pck_myhdl_07.all;

entity dffa is
    port (
        q: out std_logic;
        d: in std_logic;
        clk: in std_logic;
        rst: in std_logic
    );
end entity dffa;


architecture MyHDL of dffa is


begin




DFFA_LOGIC: process (clk, rst) is
begin
    if (rst = '0') then
        q <= '0';
    elsif rising_edge(clk) then
        q <= d;
    end if;
end process DFFA_LOGIC;

end architecture MyHDL;

myhdl/verilog/generated_myhdl/tb_dffa.v
module tb_dffa;

wire q;
reg d;
reg clk;
reg rst;

initial begin
    $from_myhdl(
        d,
        clk,
        rst
    );
    $to_myhdl(
        q
    );
end

dffa dut(
    q,
    d,
    clk,
    rst
);

endmodule

myhdl/simulation_files/tb_dffa.vcd
$date
    Fri Apr 13 11:23:25 2012
$end
$version
    MyHDL 0.7
$end
$timescale
    1ns
$end

$scope module tb_dffa $end
$var reg 1 ! q $end
$var reg 1 " rst $end
$var reg 1 # d $end
$var reg 1 $ clk $end
$scope module dffa_inst $end
$var reg 1 " rst $end
$var reg 1 ! q $end
$var reg 1 # d $end
$var reg 1 $ clk $end
$upscope $end
$upscope $end

$enddefinitions $end
$dumpvars
0!
0"
0#
0$
$end
#5
1"
#10
1$
#20
0$
#30
1$
#40
0$
#50
1$
#60
0$
#70
1$
#80
0$
1#
#90
1$
1!
#100
0$
#110
1$
#120
0$
0#
#130
1$
0!
#140
0$
#150
1$
#160
0$
#170
1$
#180
0$
#190
1$
#200
0$
#210
1$
#220
0$
1#
#230
1$
1!
#240
0$
#250
1$
#260
0$
0#
#270
1$
0!
#280
0$
#290
1$
#300
0$
#310
1$
#320
0$
1#
#330
1$
1!
#340
0$
0#
#350
1$
0!
#360
0$
#370
1$
#380
0$
1#
#390
1$
1!
#400
0$
#410
1$
#420
0$
0#
#430
1$
0!
#440
0$
#450
1$
#460
0$
1#
#470
1$
1!
#480
0$
0#
#490
1$
0!
#500
0$
1#
#510
1$
1!
#520
0$
0#
#530
1$
0!
#537
0"
#540
0$
1#
#550
1$
#560
0$
#570
1$
#580
0$
#590
1$
#600
0$
0#
#610
1$
#620
0$
1#
#621
1"
#630
1$
1!
#640
0$
0#
#650
1$
0!
#660
0$
#670
1$
#680
0$
#690
1$
#700
0$
#710
1$
#720
0$
#730
1$
#740
0$
#750
1$
#760
0$
1#
#770
1$
1!
#780
0$
#790
1$
#800
0$
#810
1$
#820
0$
#830
1$
#840
0$
#850
1$
#860
0$
0#
#870
1$
0!
#880
0$
#890
1$
#900
0$
#910
1$
#920
0$
1#
#930
1$
1!
#940
0$
#950
1$
#960
0$
0#
#970
1$
0!
#980
0$
1#
#990
1$
1!
#1000
0$
#1010
1$
#1020
0$
0#
#1030
1$
0!
#1040
0$
#1050
1$
#1060
0$
#1070
1$
#1080
0$
#1090
1$
#1100
0$
1#
#1110
1$
1!
#1120
0$
0#
#1130
1$
0!
#1140
0$
#1150
1$
#1160
0$
#1170
1$
#1180
0$
#1190
1$
#1200
0$
#1210
1$
#1220
0$
#1230
1$
#1240
0$
1#
#1250
1$
1!
#1260
0$
#1270
1$
#1280
0$
#1290
1$
#1300
0$
#1310
1$
#1320
0$
0#
#1330
1$
0!
#1340
0$
#1350
1$
#1360
0$
#1370
1$
#1380
0$
1#
#1390
1$
1!
#1400
0$
#1410
1$
#1420
0$
0#
#1430
1$
0!
#1440
0$
1#
#1450
1$
1!
#1460
0$
#1470
1$
#1480
0$
#1490
1$
#1500
0$
#1510
1$
#1520
0$
0#
#1530
1$
0!
#1540
0$
#1550
1$
#1560
0$
#1570
1$
#1580
0$
#1590
1$
#1591
0"
#1600
0$
#1610
1$
#1620
0$
1#
#1630
1$
#1640
0$
#1650
1$
#1660
0$
0#
#1670
1$
#1679
1"
#1680
0$
#1690
1$
#1700
0$
1#
#1710
1$
1!
#1720
0$
#1730
1$
#1740
0$
#1750
1$
#1760
0$
0#
#1770
1$
0!
#1780
0$
1#
#1790
1$
1!
#1800
0$
0#
#1810
1$
0!
#1820
0$
1#
#1830
1$
1!
#1840
0$
#1850
1$
#1860
0$
#1870
1$
#1880
0$
0#
#1890
1$
0!
#1900
0$
1#
#1910
1$
1!
#1920
0$
0#
#1930
1$
0!
#1940
0$
#1950
1$
#1960
0$
#1970
1$
#1980
0$
1#
#1990
1$
1!
